<?xml version="1.0" encoding="UTF-8"?>
<!--<StudentRecords xmls:soap="http://com.example.hades.SimpleXML">-->
<!--     <soap:value>123</soap:value> -->
<!--        https://blog.csdn.net/Fancy_xty/article/details/52814184-->

<!-- StuRecords -->
<StudentRecords xmls="http://com.example.hades.SimpleXML">
<!-- List<GradleRecord> gradleRecordList -->
<!-- GradleRecord -->
    <list name="grade1">

        <!-- List<StuEntry> entries -->
        <!-- StuEntry -->
        <entry id="1">
            <name>Jobs</name>
            <gender>Boy</gender>
            <phone>phone 1</phone>
            <phone>phone 2</phone>
        </entry>

        <!-- StuEntry -->
        <entry id="2">
            <name2>Helen Keller</name2>
            <gender>Girl</gender>
        </entry>
    </list>
    <list name="grade2">
        <entry id="1">
            <name>Bill</name>
            <gender>Boy</gender>
        </entry>
    </list>
<!--    <im:image height="170">111</im:image>-->
<!--         <xx im:image="170">111</xx> -->
</StudentRecords>